odoo/addons/l10n_es_ticketbai_pos/README.rst
odoo/addons/l10n_es_ticketbai_pos/__init__.py
odoo/addons/l10n_es_ticketbai_pos/__manifest__.py
odoo/addons/l10n_es_ticketbai_pos/i18n/es.po
odoo/addons/l10n_es_ticketbai_pos/i18n/l10n_es_ticketbai_pos.pot
odoo/addons/l10n_es_ticketbai_pos/models/__init__.py
odoo/addons/l10n_es_ticketbai_pos/models/account_move.py
odoo/addons/l10n_es_ticketbai_pos/models/pos_config.py
odoo/addons/l10n_es_ticketbai_pos/models/pos_order.py
odoo/addons/l10n_es_ticketbai_pos/models/ticketbai_invoice.py
odoo/addons/l10n_es_ticketbai_pos/security/ir.model.access.csv
odoo/addons/l10n_es_ticketbai_pos/static/description/icon.png
odoo/addons/l10n_es_ticketbai_pos/static/lib/qrcode.js
odoo/addons/l10n_es_ticketbai_pos/static/lib/tbai.js
odoo/addons/l10n_es_ticketbai_pos/static/src/img/oca_logo.png
odoo/addons/l10n_es_ticketbai_pos/static/src/js/db.js
odoo/addons/l10n_es_ticketbai_pos/static/src/js/models.js
odoo/addons/l10n_es_ticketbai_pos/static/src/js/screens.js
odoo/addons/l10n_es_ticketbai_pos/static/src/js/tbai_models.js
odoo/addons/l10n_es_ticketbai_pos/static/src/js/widgets.js
odoo/addons/l10n_es_ticketbai_pos/static/src/xml/pos.xml
odoo/addons/l10n_es_ticketbai_pos/tests/__init__.py
odoo/addons/l10n_es_ticketbai_pos/tests/common.py
odoo/addons/l10n_es_ticketbai_pos/tests/test_l10n_es_ticketbai_pos.py
odoo/addons/l10n_es_ticketbai_pos/views/l10n_es_ticketbai_pos.xml
odoo/addons/l10n_es_ticketbai_pos/views/l10n_es_ticketbai_pos_views.xml
odoo/addons/l10n_es_ticketbai_pos/views/pos_order_views.xml
odoo/addons/l10n_es_ticketbai_pos/views/ticketbai_certificate_views.xml
odoo13_addon_l10n_es_ticketbai_pos-13.0.1.0.5.dist-info/METADATA
odoo13_addon_l10n_es_ticketbai_pos-13.0.1.0.5.dist-info/WHEEL
odoo13_addon_l10n_es_ticketbai_pos-13.0.1.0.5.dist-info/top_level.txt
odoo13_addon_l10n_es_ticketbai_pos-13.0.1.0.5.dist-info/RECORD
