Metadata-Version: 2.1
Name: odoo13-addon-l10n-es-ticketbai-pos
Version: 13.0.1.0.5
Summary: TicketBAI - Point of Sale - declaración de todas las operaciones de venta realizadas por las personas y entidades que desarrollan actividades económicas
Home-page: https://github.com/OCA/l10n-spain
Author: Binovo,Odoo Community Association (OCA)
Author-email: support@odoo-community.org
License: AGPL-3
Platform: UNKNOWN
Classifier: Programming Language :: Python
Classifier: Framework :: Odoo
Classifier: Framework :: Odoo :: 13.0
Classifier: License :: OSI Approved :: GNU Affero General Public License v3
Classifier: Development Status :: 4 - Beta
Requires-Python: >=3.5
Requires-Dist: odoo13-addon-l10n-es-pos
Requires-Dist: odoo13-addon-l10n-es-ticketbai
Requires-Dist: odoo13-addon-pos-order-mgmt
Requires-Dist: odoo (<13.1dev,>=13.0a)
